fast_s3/__init__.py
fast_s3/fetcher.py
fast_s3/file.py
fast_s3/transfer_manager.py
fast_s3/uploader.py
fast_s3-3.0.1.dist-info/METADATA
fast_s3-3.0.1.dist-info/WHEEL
fast_s3-3.0.1.dist-info/RECORD
